codetalker/__init__.py
codetalker/apps.py
codetalker/parser.py
codetalker/settings.py
codetalker/templatetags/codetalker.py
django_codetalker-0.1.dist-info/DESCRIPTION.rst
django_codetalker-0.1.dist-info/METADATA
django_codetalker-0.1.dist-info/RECORD
django_codetalker-0.1.dist-info/WHEEL
django_codetalker-0.1.dist-info/metadata.json
django_codetalker-0.1.dist-info/top_level.txt
